README.md
pyproject.toml
setup.cfg
setup.py
quantum_dataset.egg-info/PKG-INFO
quantum_dataset.egg-info/SOURCES.txt
quantum_dataset.egg-info/dependency_links.txt
quantum_dataset.egg-info/not-zip-safe
quantum_dataset.egg-info/requires.txt
quantum_dataset.egg-info/top_level.txt
quantumdataset/__init__.py
quantumdataset/quantum_dataset.py
quantumdataset/quantum_dataset2.py
quantumdataset/version.py
quantumdataset/xarray_utils.py
quantumdataset/externals/__init__.py
quantumdataset/externals/markup.py
quantumdataset/externals/serialization.py