Metadata-Version: 2.1
Name: quantum-dataset
Version: 0.2.4
Summary: Collection of measurements on quantum devices
Home-page: https://github.com/QuTech-Delft/quantum_dataset/
Author: Pieter Eendebak
Author-email: pieter.eendebak@tno.nl
Maintainer: Pieter Eendebak
Maintainer-email: pieter.eendebak@tno.nl
License: MIT
Classifier: Development Status :: 3 - Alpha
Classifier: Intended Audience :: Science/Research
Classifier: Programming Language :: Python :: 3
Classifier: Programming Language :: Python :: 3.10
Classifier: Programming Language :: Python :: 3.11
Classifier: Topic :: Scientific/Engineering
